stmeasures/__init__.py
stmeasures/_algorithms.py
stmeasures/calculates.py
stmeasures/read.py
stmeasures/validation.py
stmeasures/visualize.py
stmeasures/calculate/__init__.py
stmeasures/calculate/base.py
stmeasures/calculate/dtw.py
stmeasures/calculate/editdistance.py
stmeasures/calculate/euclidean.py
stmeasures/calculate/frechet.py
stmeasures/calculate/hausdorff.py
stmeasures/calculate/lcss.py
stmeasures/calculate/manhattan.py
stmeasures/calculate/rdp.py
stmeasures/calculate/sad.py
stmeasures/objects/cstructures.py
stmeasures/objects/geojson.py
stmeasures-clib/libdtw.so
stmeasures-clib/libeditdist.so
stmeasures-clib/libeuclidean.so
stmeasures-clib/libfrechet.so
stmeasures-clib/libhausdorff.so
stmeasures-clib/liblcss.so
stmeasures-clib/libmanhattan.so
stmeasures-clib/librdp.so
stmeasures-clib/libsad.so
stmeasures-0.0.1.1.dist-info/METADATA
stmeasures-0.0.1.1.dist-info/WHEEL
stmeasures-0.0.1.1.dist-info/licenses/LICENSE
stmeasures-0.0.1.1.dist-info/RECORD
