Metadata-Version: 2.3
Name: stmeasures
Version: 0.0.1.1
Summary: A library for measuring trajectory similarities.
Project-URL: Documentation, https://stmeasures.readthedocs.io/en/latest/
Project-URL: Repository, https://github.com/TT2024-B106/stmeasures.git
Project-URL: Issues, https://github.com/TT2024-B106/stmeasures/issues
Author: Amilcar Meneses, Erika Hernandez
Author-email: Eduardo Mendoza <emendozam1501@alumno.ipn.mx>, Javier Munguia <fmunguiag1400@alumno.ipn.mx>, Marco Ortega <mortegaf1500@alumno.ipn.mx>
Maintainer-email: Eduardo Mendoza <emendozam1501@alumno.ipn.mx>, Javier Munguia <fmunguiag1400@alumno.ipn.mx>, Marco Ortega <mortegaf1500@alumno.ipn.mx>
License: MIT License
Keywords: geojson,measurement similarities,mobile devices,mobility patterns,trajectory similarities
Classifier: Development Status :: 3 - Alpha
Classifier: Intended Audience :: Developers
Classifier: License :: OSI Approved :: MIT License
Classifier: Programming Language :: Python :: 3
Classifier: Programming Language :: Python :: 3.10
Classifier: Programming Language :: Python :: 3.11
Classifier: Programming Language :: Python :: 3.12
Classifier: Topic :: Scientific/Engineering :: GIS
Requires-Python: >=3.8
